{
  "notes": [
    {
      "title": "Hassana",
      "details": "She is the one am in love with right now. Yes we have our issues but we will be fine",
      "category": "work",
      "id": 1
    },
    {
      "title": "Prime College",
      "details": "This is a place i work, yes they pay me well but am tire of the teaching profession and will like to change into IT",
      "category": "work",
      "id": 2
    },
    {
      "title": "My Father",
      "details": "I miss you and i have not stopped missing you since then. I regret certain things I should have done but did not, am sorry",
      "category": "reminder",
      "id": 4
    },
    {
      "title": "Toni Braxton",
      "details": "She is a greate misician and good at what she does, she is also a pastors daughter",
      "category": "money",
      "id": 5
    }
  ]
}